s3_reader/__init__.py
s3_reader/file.py
s3_reader/py.typed
s3_reader/version.py
s3_reader-0.3.9.dist-info/WHEEL
s3_reader-0.3.9.dist-info/METADATA
s3_reader-0.3.9.dist-info/RECORD
