Metadata-Version: 2.4
Name: s3-reader
Version: 0.3.9
Summary: Python library to read S3 file as local file.
Keywords: aws,s3,file,read
Author: rcmdnk
Author-email: rcmdnk <rcmdnk@gmail.com>
License-Expression: Apache-2.0
Requires-Dist: boto3-session>=0.0.8
Requires-Python: >=3.9
Project-URL: Documentation, https://github.com/rcmdnk/s3-reader
Project-URL: Homepage, https://github.com/rcmdnk/s3-reader
Project-URL: Issue, https://github.com/rcmdnk/s3-reader/issues
Project-URL: Repository, https://github.com/rcmdnk/s3-reader
